08_decoder_3to8/decoder_3to8.v
module decoder_3to8(
    input [2:0] a,
    output reg [7:0] y
);

always @(*) begin
    case (a)
        3'b000: y = 8'b00000001;
        3'b001: y = 8'b00000010;
        3'b010: y = 8'b00000100;
        3'b011: y = 8'b00001000;
        3'b100: y = 8'b00010000;
        3'b101: y = 8'b00100000;
        3'b110: y = 8'b01000000;
        3'b111: y = 8'b10000000;
        default: y = 8'b00000000;
    endcase
end
endmodule

08_decoder_3to8/decoder_3to8_tb.v
module decoder_3to8_tb;

    reg [2:0] a;
    wire [7:0] y;

    decoder_3to8 uut (
        .a(a),
        .y(y)
    );

    integer i;
    initial begin
        $dumpfile("dump.vcd");
        $dumpvars(0, decoder_3to8_tb);
        for (i = 0; i < 8; i = i + 1) begin
            a = i;
            #10;
            $display("A = %b | Y = %b", a, y);
        end
        $finish;
    end

endmodule

08_decoder_3to8/dump.vcd
$date
	Sun Sep 20 20:28:48 2026
$end
$version
	Icarus Verilog
$end
$timescale
	1s
$end
$scope module decoder_3to8_tb $end
$var wire 8 ! y [7:0] $end
$var reg 3 " a [2:0] $end
$var integer 32 # i [31:0] $end
$scope module uut $end
$var wire 3 $ a [2:0] $end
$var reg 8 % y [7:0] $end
$upscope $end
$upscope $end
$enddefinitions $end
#0
$dumpvars
b1 %
b0 $
b0 #
b0 "
b1 !
$end
#10
b10 !
b10 %
b1 "
b1 $
b1 #
#20
b100 !
b100 %
b10 "
b10 $
b10 #
#30
b1000 !
b1000 %
b11 "
b11 $
b11 #
#40
b10000 !
b10000 %
b100 "
b100 $
b100 #
#50
b100000 !
b100000 %
b101 "
b101 $
b101 #
#60
b1000000 !
b1000000 %
b110 "
b110 $
b110 #
#70
b10000000 !
b10000000 %
b111 "
b111 $
b111 #
#80
b1000 #
