06_mux_16to1/mux_16to1.v
module mux_16x1(
    input [15:0] i,
    input [3:0] s,
    output reg out
);

always @(*) begin
    case (s)
        4'b0000: out = i[0];
        4'b0001: out = i[1];
        4'b0010: out = i[2];
        4'b0011: out = i[3];
        4'b0100: out = i[4];
        4'b0101: out = i[5];
        4'b0110: out = i[6];
        4'b0111: out = i[7];
        4'b1000: out = i[8];
        4'b1001: out = i[9];
        4'b1010: out = i[10];
        4'b1011: out = i[11];
        4'b1100: out = i[12];
        4'b1101: out = i[13];
        4'b1110: out = i[14];
        4'b1111: out = i[15];
        default: out = 1'b0;
    endcase
end
endmodule

06_mux_16to1/mux_16to1_tb.v
module mux_16x1_tb;

    reg [15:0] i;
    reg [3:0] s;
    wire out;

    mux_16x1 uut (
        .i(i),
        .s(s),
        .out(out)
    );

    integer j;

    initial begin
        $dumpfile("dump.vcd");
        $dumpvars(0, mux_16x1_tb);
        i = 16'b1010101010101010;

        for (j = 0; j < 16; j = j + 1) begin
            s = j;
            #10;
            $display("i = %b | s = %b | out = %b",i, s, out);
        end
        $finish;
    end
endmodule

06_mux_16to1/dump.vcd
$date
	Thu Sep 17 21:05:04 2026
$end
$version
	Icarus Verilog
$end
$timescale
	1s
$end
$scope module mux_16x1_tb $end
$var wire 1 ! out $end
$var reg 16 " i [15:0] $end
$var reg 4 # s [3:0] $end
$var integer 32 $ j [31:0] $end
$scope module uut $end
$var wire 16 % i [15:0] $end
$var wire 4 & s [3:0] $end
$var reg 1 ! out $end
$upscope $end
$upscope $end
$enddefinitions $end
#0
$dumpvars
b0 &
b1010101010101010 %
b0 $
b0 #
b1010101010101010 "
0!
$end
#10
1!
b1 #
b1 &
b1 $
#20
0!
b10 #
b10 &
b10 $
#30
1!
b11 #
b11 &
b11 $
#40
0!
b100 #
b100 &
b100 $
#50
1!
b101 #
b101 &
b101 $
#60
0!
b110 #
b110 &
b110 $
#70
1!
b111 #
b111 &
b111 $
#80
0!
b1000 #
b1000 &
b1000 $
#90
1!
b1001 #
b1001 &
b1001 $
#100
0!
b1010 #
b1010 &
b1010 $
#110
1!
b1011 #
b1011 &
b1011 $
#120
0!
b1100 #
b1100 &
b1100 $
#130
1!
b1101 #
b1101 &
b1101 $
#140
0!
b1110 #
b1110 &
b1110 $
#150
1!
b1111 #
b1111 &
b1111 $
#160
b10000 $
