15_parity_generator/parity_generator.v

// Even Parity Generator
module parity_generator (
    input  [3:0] b,
    output       y
);

    assign y = ^b;

endmodule


//Odd Parity Generator
/*
module parity_generator (
    input  [3:0] b,
    output       y
);

    assign y = ~^b;

endmodule
*/

15_parity_generator/parity_generator_tb.v
module parity_generator_tb;
    reg  [3:0] b;
    wire y;

    parity_generator uut (
        .b(b),
        .y(y)
    );

    integer i;

    initial begin
        $dumpfile("dump.vcd");
        $dumpvars(0, parity_generator_tb);

        for (i = 0; i < 16; i = i + 1) begin
            b = i;
            #10;
            $display("Data = %b | Parity = %b", b, y);
        end
        $finish;
    end
endmodule

15_parity_generator/dump.vcd
$date
	Fri Oct 02 11:07:37 2026
$end
$version
	Icarus Verilog
$end
$timescale
	1s
$end
$scope module parity_generator_tb $end
$var wire 1 ! y $end
$var reg 4 " b [3:0] $end
$var integer 32 # i [31:0] $end
$scope module uut $end
$var wire 4 $ b [3:0] $end
$var wire 1 ! y $end
$upscope $end
$upscope $end
$enddefinitions $end
#0
$dumpvars
b0 $
b0 #
b0 "
0!
$end
#10
1!
b1 "
b1 $
b1 #
#20
b10 "
b10 $
b10 #
#30
0!
b11 "
b11 $
b11 #
#40
1!
b100 "
b100 $
b100 #
#50
0!
b101 "
b101 $
b101 #
#60
b110 "
b110 $
b110 #
#70
1!
b111 "
b111 $
b111 #
#80
b1000 "
b1000 $
b1000 #
#90
0!
b1001 "
b1001 $
b1001 #
#100
b1010 "
b1010 $
b1010 #
#110
1!
b1011 "
b1011 $
b1011 #
#120
0!
b1100 "
b1100 $
b1100 #
#130
1!
b1101 "
b1101 $
b1101 #
#140
b1110 "
b1110 $
b1110 #
#150
0!
b1111 "
b1111 $
b1111 #
#160
b10000 #
