18_seqdet_1101_moore/seqdet_1101_moore.v
module seqdet_1101_moore(
    input rst,
    input din,
    input clk,
    output detected
);
    parameter S0 = 3'b000,
              S1 = 3'b001,
              S2 = 3'b010,
              S3 = 3'b011,
              S4 = 3'b101;

    reg [2:0] state,next_state;

    always@(posedge clk or posedge rst) begin
        if(rst)
            state <= S0;
        else 
            state <= next_state;
    end

    always @(*) begin

        case (state)

            S0: begin
                if (din)
                    next_state = S1;
                else
                    next_state = S0;
            end

            S1: begin
                if (din)
                    next_state = S2;
                else
                    next_state = S0;
            end

            S2: begin
                if (din)
                    next_state = S2;
                else
                    next_state = S3;
            end

            S3: begin
                if (din)
                    next_state = S4;
                else
                    next_state = S0;
            end

            S4: begin
                if (din)
                    next_state = S2;
                else
                    next_state = S0;
            end

            default:
                next_state = S0;

        endcase
    end

    assign detected = (state == S4);

endmodule

18_seqdet_1101_moore/seqdet_1101_moore_tb.v
module seqdet_1101_moore_tb;
    reg clk;
    reg rst;
    reg din;
    wire detected;

    seqdet_1101_moore uut (
        .rst(rst),
        .din(din),
        .clk(clk),
        .detected(detected)
    );

    always #5 clk = ~clk;

    initial begin
        clk = 0;
        rst = 1;
        din = 0;

        $dumpfile("dump.vcd");
        $dumpvars(0, seqdet_1101_moore_tb);

        $monitor("Time=%0t | rst=%b | din=%b | detected=%b",$time, rst, din, detected);

        #12;
        rst = 0;
        @(negedge clk) din = 1;
        @(negedge clk) din = 1;
        @(negedge clk) din = 0;
        @(negedge clk) din = 1;
        @(negedge clk);
        @(negedge clk) din = 1;
        @(negedge clk) din = 0;
        @(negedge clk) din = 1;

        @(negedge clk);

        #10 $finish;
    end

endmodule

18_seqdet_1101_moore/dump.vcd
$date
	Tue Oct 06 12:05:57 2026
$end
$version
	Icarus Verilog
$end
$timescale
	1s
$end
$scope module seqdet_1101_moore_tb $end
$var wire 1 ! detected $end
$var reg 1 " clk $end
$var reg 1 # din $end
$var reg 1 $ rst $end
$scope module uut $end
$var wire 1 " clk $end
$var wire 1 # din $end
$var wire 1 $ rst $end
$var wire 1 ! detected $end
$var reg 3 % next_state [2:0] $end
$var reg 3 & state [2:0] $end
$upscope $end
$upscope $end
$enddefinitions $end
#0
$dumpvars
b0 &
b0 %
1$
0#
0"
0!
$end
#5
1"
#10
0"
#12
0$
#15
1"
#20
b1 %
1#
0"
#25
b10 %
b1 &
1"
#30
0"
#35
b10 &
1"
#40
b11 %
0#
0"
#45
b0 %
b11 &
1"
#50
b101 %
1#
0"
#55
b10 %
1!
b101 &
1"
#60
0"
#65
0!
b10 &
1"
#70
0"
#75
1"
#80
b11 %
0#
0"
#85
b0 %
b11 &
1"
#90
b101 %
1#
0"
#95
b10 %
1!
b101 &
1"
#100
0"
#105
0!
b10 &
1"
