10_demux_1to8/demux_1to8.v
module demux_1to8 (
    input       i,
    input [2:0] sel,
    output reg [7:0] y
);

always @(*) begin
    y = 8'b00000000;
    case (sel)
        3'b000: y[0] = i;
        3'b001: y[1] = i;
        3'b010: y[2] = i;
        3'b011: y[3] = i;
        3'b100: y[4] = i;
        3'b101: y[5] = i;
        3'b110: y[6] = i;
        3'b111: y[7] = i;
    endcase
end
endmodule

10_demux_1to8/demux_1to8_tb.v
module demux_1to8_tb;
    reg i;
    reg [2:0] sel;
    wire [7:0] y;

    demux_1to8 uut (.i(i),.sel(sel),.y(y));

    integer j;

    initial begin
        $dumpfile("demux.vcd");
        $dumpvars(0, demux_1to8_tb);
        $monitor("Time=%0t | i=%b | sel=%b | y=%b",$time, i, sel, y);

        i = 1'b1;

        for (j = 0; j < 8; j = j + 1) begin
            sel = j;
            #10;
        end

        i = 1'b0;
        #10;
        $finish;
    end
endmodule

10_demux_1to8/demux.vcd
$date
	Tue Sep 22 21:43:28 2026
$end
$version
	Icarus Verilog
$end
$timescale
	1s
$end
$scope module demux_1to8_tb $end
$var wire 8 ! y [7:0] $end
$var reg 1 " i $end
$var reg 3 # sel [2:0] $end
$var integer 32 $ j [31:0] $end
$scope module uut $end
$var wire 1 " i $end
$var wire 3 % sel [2:0] $end
$var reg 8 & y [7:0] $end
$upscope $end
$upscope $end
$enddefinitions $end
#0
$dumpvars
b1 &
b0 %
b0 $
b0 #
1"
b1 !
$end
#10
b10 !
b10 &
b1 #
b1 %
b1 $
#20
b100 !
b100 &
b10 #
b10 %
b10 $
#30
b1000 !
b1000 &
b11 #
b11 %
b11 $
#40
b10000 !
b10000 &
b100 #
b100 %
b100 $
#50
b100000 !
b100000 &
b101 #
b101 %
b101 $
#60
b1000000 !
b1000000 &
b110 #
b110 %
b110 $
#70
b10000000 !
b10000000 &
b111 #
b111 %
b111 $
#80
b0 !
b0 &
0"
b1000 $
