09_decoder_4to16/decoder_4to16.v
module decoder_4to16(
    input [3:0] a,
    output [15:0] y
);

assign y = 16'b0000000000000001 << a;

endmodule

09_decoder_4to16/decoder_4to16_tb.v
module decoder_4to16_tb;
    reg [3:0] a;
    wire [15:0] y;

    decoder_4to16 uut (.a(a),.y(y));

    integer i;
    initial begin
        $dumpfile("dump.vcd");
        $dumpvars(0, decoder_4to16_tb);

        for (i = 0; i < 16; i = i + 1) begin
            a = i;
            #10;
            $display("A = %b | Y = %b", a, y);
        end
        $finish;
    end

endmodule

09_decoder_4to16/dump.vcd
$date
	Mon Sep 21 19:54:31 2026
$end
$version
	Icarus Verilog
$end
$timescale
	1s
$end
$scope module decoder_4to16_tb $end
$var wire 16 ! y [15:0] $end
$var reg 4 " a [3:0] $end
$var integer 32 # i [31:0] $end
$scope module uut $end
$var wire 4 $ a [3:0] $end
$var wire 16 % y [15:0] $end
$upscope $end
$upscope $end
$enddefinitions $end
#0
$dumpvars
b1 %
b0 $
b0 #
b0 "
b1 !
$end
#10
b10 !
b10 %
b1 "
b1 $
b1 #
#20
b100 !
b100 %
b10 "
b10 $
b10 #
#30
b1000 !
b1000 %
b11 "
b11 $
b11 #
#40
b10000 !
b10000 %
b100 "
b100 $
b100 #
#50
b100000 !
b100000 %
b101 "
b101 $
b101 #
#60
b1000000 !
b1000000 %
b110 "
b110 $
b110 #
#70
b10000000 !
b10000000 %
b111 "
b111 $
b111 #
#80
b100000000 !
b100000000 %
b1000 "
b1000 $
b1000 #
#90
b1000000000 !
b1000000000 %
b1001 "
b1001 $
b1001 #
#100
b10000000000 !
b10000000000 %
b1010 "
b1010 $
b1010 #
#110
b100000000000 !
b100000000000 %
b1011 "
b1011 $
b1011 #
#120
b1000000000000 !
b1000000000000 %
b1100 "
b1100 $
b1100 #
#130
b10000000000000 !
b10000000000000 %
b1101 "
b1101 $
b1101 #
#140
b100000000000000 !
b100000000000000 %
b1110 "
b1110 $
b1110 #
#150
b1000000000000000 !
b1000000000000000 %
b1111 "
b1111 $
b1111 #
#160
b10000 #
