04_excess3_to_bcd/excess3_to_bcd.v
module excess3_to_bcd (
    input  [3:0] excess3,
    output [3:0] bcd
);

    assign bcd = (excess3 >= 4'b0011 && excess3 <= 4'b1100)
                 ? excess3 - 4'b0011
                 : 4'bxxxx;

endmodule

04_excess3_to_bcd/excess3_to_bcd_tb.v
module excess3_to_bcd_tb;
    reg  [3:0] excess3;
    wire [3:0] bcd;
    integer i;

    excess3_to_bcd uut (
        .excess3(excess3),
        .bcd(bcd)
    );

    initial begin
        $dumpfile("dump.vcd");
        $dumpvars(0, excess3_to_bcd_tb);
        $monitor("Time=%0t | Excess-3=%b | BCD=%b",
                 $time, excess3, bcd);

        for (i = 0; i < 16; i = i + 1) begin
            excess3 = i;
            #10;
        end

        $finish;
    end

endmodule

04_excess3_to_bcd/dump.vcd
$date
	Wed Sep 16 22:02:16 2026
$end
$version
	Icarus Verilog
$end
$timescale
	1s
$end
$scope module excess3_to_bcd_tb $end
$var wire 4 ! bcd [3:0] $end
$var reg 4 " excess3 [3:0] $end
$var integer 32 # i [31:0] $end
$scope module uut $end
$var wire 4 $ excess3 [3:0] $end
$var wire 4 % bcd [3:0] $end
$upscope $end
$upscope $end
$enddefinitions $end
#0
$dumpvars
bx %
b0 $
b0 #
b0 "
bx !
$end
#10
b1 "
b1 $
b1 #
#20
b10 "
b10 $
b10 #
#30
b0 !
b0 %
b11 "
b11 $
b11 #
#40
b1 !
b1 %
b100 "
b100 $
b100 #
#50
b10 !
b10 %
b101 "
b101 $
b101 #
#60
b11 !
b11 %
b110 "
b110 $
b110 #
#70
b100 !
b100 %
b111 "
b111 $
b111 #
#80
b101 !
b101 %
b1000 "
b1000 $
b1000 #
#90
b110 !
b110 %
b1001 "
b1001 $
b1001 #
#100
b111 !
b111 %
b1010 "
b1010 $
b1010 #
#110
b1000 !
b1000 %
b1011 "
b1011 $
b1011 #
#120
b1001 !
b1001 %
b1100 "
b1100 $
b1100 #
#130
bx !
bx %
b1101 "
b1101 $
b1101 #
#140
b1110 "
b1110 $
b1110 #
#150
b1111 "
b1111 $
b1111 #
#160
b10000 #
